quicktions.cpython-313t-x86_64-linux-gnu.so
quicktions-1.21.dist-info/METADATA
quicktions-1.21.dist-info/WHEEL
quicktions-1.21.dist-info/top_level.txt
quicktions-1.21.dist-info/RECORD
quicktions-1.21.dist-info/licenses/LICENSE
