Metadata-Version: 2.4
Name: quicktions
Version: 1.21
Summary: Fast fractions data type for rational numbers. Cythonized version of 'fractions.Fraction'.
Home-page: https://github.com/scoder/quicktions
Author: Stefan Behnel
Author-email: stefan_ml@behnel.de
Classifier: Development Status :: 6 - Mature
Classifier: Intended Audience :: Developers
Classifier: Operating System :: OS Independent
Classifier: Programming Language :: Python
Classifier: Programming Language :: Python :: 3
Classifier: Programming Language :: Cython
Classifier: Topic :: Scientific/Engineering :: Mathematics
Classifier: Topic :: Office/Business :: Financial
Classifier: License :: OSI Approved :: Python Software Foundation License
License-File: LICENSE
Dynamic: author
Dynamic: author-email
Dynamic: classifier
Dynamic: description
Dynamic: home-page
Dynamic: license-file
Dynamic: summary
